oneapi2langchain/__init__.py
oneapi2langchain/baidu_qianfan.py
oneapi2langchain/spark.py
oneapi2langchain/sparkai/__init__.py
oneapi2langchain/sparkai/api_resources/__init__.py
oneapi2langchain/sparkai/api_resources/chat_completion.py
oneapi2langchain/sparkai/deprecation.py
oneapi2langchain/sparkai/errors/__init__.py
oneapi2langchain/sparkai/http_retry/__init__.py
oneapi2langchain/sparkai/http_retry/async_handler.py
oneapi2langchain/sparkai/http_retry/builtin_async_handlers.py
oneapi2langchain/sparkai/http_retry/builtin_handlers.py
oneapi2langchain/sparkai/http_retry/builtin_interval_calculators.py
oneapi2langchain/sparkai/http_retry/handler.py
oneapi2langchain/sparkai/http_retry/interval_calculator.py
oneapi2langchain/sparkai/http_retry/jitter.py
oneapi2langchain/sparkai/http_retry/request.py
oneapi2langchain/sparkai/http_retry/response.py
oneapi2langchain/sparkai/http_retry/state.py
oneapi2langchain/sparkai/log/__init__.py
oneapi2langchain/sparkai/log/logger.py
oneapi2langchain/sparkai/memory/__init__.py
oneapi2langchain/sparkai/memory/buffer.py
oneapi2langchain/sparkai/memory/buffer_window.py
oneapi2langchain/sparkai/memory/chat_memory.py
oneapi2langchain/sparkai/memory/chat_message_histories/__init__.py
oneapi2langchain/sparkai/memory/chat_message_histories/dynamodb.py
oneapi2langchain/sparkai/memory/chat_message_histories/file.py
oneapi2langchain/sparkai/memory/chat_message_histories/in_memory.py
oneapi2langchain/sparkai/memory/chat_message_histories/postgres.py
oneapi2langchain/sparkai/memory/chat_message_histories/redis.py
oneapi2langchain/sparkai/memory/combined.py
oneapi2langchain/sparkai/memory/readonly.py
oneapi2langchain/sparkai/memory/simple.py
oneapi2langchain/sparkai/memory/token_buffer.py
oneapi2langchain/sparkai/memory/utils.py
oneapi2langchain/sparkai/models/__init__.py
oneapi2langchain/sparkai/models/basic_objects.py
oneapi2langchain/sparkai/models/chat/__init__.py
oneapi2langchain/sparkai/prompts/classification/__init__.py
oneapi2langchain-0.0.102.dist-info/LICENSE
oneapi2langchain-0.0.102.dist-info/METADATA
oneapi2langchain-0.0.102.dist-info/WHEEL
oneapi2langchain-0.0.102.dist-info/RECORD
