Metadata-Version: 2.1
Name: oneapi2langchain
Version: 0.0.102
Summary: langchain实现的闭源模型统一API
Home-page: https://github.com/shell-nlp/oneapi2langchain
License: MIT
Author: liuyu
Author-email: 506610466@qq.com
Requires-Python: >=3.10,<4.0
Classifier: License :: OSI Approved :: MIT License
Classifier: Programming Language :: Python :: 3
Classifier: Programming Language :: Python :: 3.10
Classifier: Programming Language :: Python :: 3.11
Classifier: Programming Language :: Python :: 3.12
Requires-Dist: langchain (>=0.0.321) ; python_full_version >= "3.8.1"
Project-URL: Repository, https://github.com/shell-nlp/oneapi2langchain
